{
    "version": "0.14.0",
    "description": "The command center that puts AI coding on steroids.",
    "homepage": "https://github.com/NeuralNomadsAI/CodeNomad",
    "license": "MIT",
    "depends": "journey/opencode",
    "architecture": {
        "64bit": {
            "url": "https://github.com/NeuralNomadsAI/CodeNomad/releases/download/v0.14.0/CodeNomad-0.14.0-win-x64.zip",
            "hash": "1ab68c2951c32fa1e60f0e7976225f44e37228f1fe5b9d0a0bacdfb379a3c944"
        }
    },
    "bin": "CodeNomad.exe",
    "shortcuts": [
        [
            "CodeNomad.exe",
            "CodeNomad"
        ]
    ],
    "checkver": {
        "github": "https://github.com/NeuralNomadsAI/CodeNomad"
    },
    "autoupdate": {
        "architecture": {
            "64bit": {
                "url": "https://github.com/NeuralNomadsAI/CodeNomad/releases/download/v$version/CodeNomad-$version-win-x64.zip"
            }
        }
    }
}
